{
  "deckTotal": 2,
  "items": [
    {
      "rank": 1,
      "name": "Chansey",
      "found": 2,
      "total": 2,
      "pct": 100.0,
      "dist": [
        {
          "copies": 4,
          "players": 2,
          "percent": 100.0
        }
      ],
      "set": "TWM",
      "number": "133",
      "uid": "Chansey::TWM::133"
    },
    {
      "rank": 2,
      "name": "Blissey ex",
      "found": 2,
      "total": 2,
      "pct": 100.0,
      "dist": [
        {
          "copies": 4,
          "players": 2,
          "percent": 100.0
        }
      ],
      "set": "TWM",
      "number": "134",
      "uid": "Blissey ex::TWM::134"
    },
    {
      "rank": 3,
      "name": "Munkidori",
      "found": 2,
      "total": 2,
      "pct": 100.0,
      "dist": [
        {
          "copies": 4,
          "players": 2,
          "percent": 100.0
        }
      ],
      "set": "TWM",
      "number": "095",
      "uid": "Munkidori::TWM::095"
    },
    {
      "rank": 4,
      "name": "Roaring Moon ex",
      "found": 2,
      "total": 2,
      "pct": 100.0,
      "dist": [
        {
          "copies": 1,
          "players": 2,
          "percent": 100.0
        }
      ],
      "set": "PAR",
      "number": "124",
      "uid": "Roaring Moon ex::PAR::124"
    },
    {
      "rank": 5,
      "name": "Cornerstone Mask Ogerpon ex",
      "found": 2,
      "total": 2,
      "pct": 100.0,
      "dist": [
        {
          "copies": 1,
          "players": 2,
          "percent": 100.0
        }
      ],
      "set": "TWM",
      "number": "112",
      "uid": "Cornerstone Mask Ogerpon ex::TWM::112"
    },
    {
      "rank": 6,
      "name": "Arven",
      "found": 2,
      "total": 2,
      "pct": 100.0,
      "dist": [
        {
          "copies": 4,
          "players": 2,
          "percent": 100.0
        }
      ]
    },
    {
      "rank": 7,
      "name": "Boss's Orders",
      "found": 2,
      "total": 2,
      "pct": 100.0,
      "dist": [
        {
          "copies": 4,
          "players": 2,
          "percent": 100.0
        }
      ]
    },
    {
      "rank": 8,
      "name": "Iono",
      "found": 2,
      "total": 2,
      "pct": 100.0,
      "dist": [
        {
          "copies": 3,
          "players": 2,
          "percent": 100.0
        }
      ]
    },
    {
      "rank": 9,
      "name": "Professor's Research",
      "found": 2,
      "total": 2,
      "pct": 100.0,
      "dist": [
        {
          "copies": 2,
          "players": 2,
          "percent": 100.0
        }
      ]
    },
    {
      "rank": 10,
      "name": "Pokégear 3.0",
      "found": 2,
      "total": 2,
      "pct": 100.0,
      "dist": [
        {
          "copies": 4,
          "players": 2,
          "percent": 100.0
        }
      ]
    },
    {
      "rank": 11,
      "name": "Ultra Ball",
      "found": 2,
      "total": 2,
      "pct": 100.0,
      "dist": [
        {
          "copies": 4,
          "players": 2,
          "percent": 100.0
        }
      ]
    },
    {
      "rank": 12,
      "name": "Nest Ball",
      "found": 2,
      "total": 2,
      "pct": 100.0,
      "dist": [
        {
          "copies": 2,
          "players": 2,
          "percent": 100.0
        }
      ]
    },
    {
      "rank": 13,
      "name": "Night Stretcher",
      "found": 2,
      "total": 2,
      "pct": 100.0,
      "dist": [
        {
          "copies": 2,
          "players": 2,
          "percent": 100.0
        }
      ]
    },
    {
      "rank": 14,
      "name": "Precious Trolley",
      "found": 2,
      "total": 2,
      "pct": 100.0,
      "dist": [
        {
          "copies": 1,
          "players": 2,
          "percent": 100.0
        }
      ]
    },
    {
      "rank": 15,
      "name": "Earthen Vessel",
      "found": 2,
      "total": 2,
      "pct": 100.0,
      "dist": [
        {
          "copies": 1,
          "players": 2,
          "percent": 100.0
        }
      ]
    },
    {
      "rank": 16,
      "name": "Switch",
      "found": 2,
      "total": 2,
      "pct": 100.0,
      "dist": [
        {
          "copies": 1,
          "players": 2,
          "percent": 100.0
        }
      ]
    },
    {
      "rank": 17,
      "name": "Technical Machine: Turbo Energize",
      "found": 2,
      "total": 2,
      "pct": 100.0,
      "dist": [
        {
          "copies": 2,
          "players": 2,
          "percent": 100.0
        }
      ]
    },
    {
      "rank": 18,
      "name": "Rigid Band",
      "found": 2,
      "total": 2,
      "pct": 100.0,
      "dist": [
        {
          "copies": 2,
          "players": 2,
          "percent": 100.0
        }
      ]
    },
    {
      "rank": 19,
      "name": "Rescue Board",
      "found": 2,
      "total": 2,
      "pct": 100.0,
      "dist": [
        {
          "copies": 1,
          "players": 2,
          "percent": 100.0
        }
      ]
    },
    {
      "rank": 20,
      "name": "Exp. Share",
      "found": 2,
      "total": 2,
      "pct": 100.0,
      "dist": [
        {
          "copies": 1,
          "players": 2,
          "percent": 100.0
        }
      ]
    },
    {
      "rank": 21,
      "name": "Town Store",
      "found": 2,
      "total": 2,
      "pct": 100.0,
      "dist": [
        {
          "copies": 2,
          "players": 2,
          "percent": 100.0
        }
      ]
    },
    {
      "rank": 22,
      "name": "Darkness Energy",
      "found": 2,
      "total": 2,
      "pct": 100.0,
      "dist": [
        {
          "copies": 7,
          "players": 2,
          "percent": 100.0
        }
      ]
    },
    {
      "rank": 23,
      "name": "Fighting Energy",
      "found": 2,
      "total": 2,
      "pct": 100.0,
      "dist": [
        {
          "copies": 2,
          "players": 2,
          "percent": 100.0
        }
      ]
    },
    {
      "rank": 24,
      "name": "Psychic Energy",
      "found": 2,
      "total": 2,
      "pct": 100.0,
      "dist": [
        {
          "copies": 1,
          "players": 2,
          "percent": 100.0
        }
      ]
    }
  ]
}