{
  "deckTotal": 1,
  "items": [
    {
      "rank": 1,
      "name": "Torchic",
      "found": 1,
      "total": 1,
      "pct": 100.0,
      "dist": [
        {
          "copies": 3,
          "players": 1,
          "percent": 100.0
        }
      ],
      "set": "JTG",
      "number": "022",
      "uid": "Torchic::JTG::022"
    },
    {
      "rank": 2,
      "name": "Combusken",
      "found": 1,
      "total": 1,
      "pct": 100.0,
      "dist": [
        {
          "copies": 1,
          "players": 1,
          "percent": 100.0
        }
      ],
      "set": "JTG",
      "number": "023",
      "uid": "Combusken::JTG::023"
    },
    {
      "rank": 3,
      "name": "Blaziken ex",
      "found": 1,
      "total": 1,
      "pct": 100.0,
      "dist": [
        {
          "copies": 3,
          "players": 1,
          "percent": 100.0
        }
      ],
      "set": "JTG",
      "number": "024",
      "uid": "Blaziken ex::JTG::024"
    },
    {
      "rank": 4,
      "name": "Froakie",
      "found": 1,
      "total": 1,
      "pct": 100.0,
      "dist": [
        {
          "copies": 2,
          "players": 1,
          "percent": 100.0
        }
      ],
      "set": "OBF",
      "number": "056",
      "uid": "Froakie::OBF::056"
    },
    {
      "rank": 5,
      "name": "Frogadier",
      "found": 1,
      "total": 1,
      "pct": 100.0,
      "dist": [
        {
          "copies": 1,
          "players": 1,
          "percent": 100.0
        }
      ],
      "set": "TWM",
      "number": "057",
      "uid": "Frogadier::TWM::057"
    },
    {
      "rank": 6,
      "name": "Greninja ex",
      "found": 1,
      "total": 1,
      "pct": 100.0,
      "dist": [
        {
          "copies": 2,
          "players": 1,
          "percent": 100.0
        }
      ],
      "set": "TWM",
      "number": "106",
      "uid": "Greninja ex::TWM::106"
    },
    {
      "rank": 7,
      "name": "N's Zorua",
      "found": 1,
      "total": 1,
      "pct": 100.0,
      "dist": [
        {
          "copies": 2,
          "players": 1,
          "percent": 100.0
        }
      ],
      "set": "JTG",
      "number": "097",
      "uid": "N's Zorua::JTG::097"
    },
    {
      "rank": 8,
      "name": "N's Zoroark ex",
      "found": 1,
      "total": 1,
      "pct": 100.0,
      "dist": [
        {
          "copies": 2,
          "players": 1,
          "percent": 100.0
        }
      ],
      "set": "JTG",
      "number": "098",
      "uid": "N's Zoroark ex::JTG::098"
    },
    {
      "rank": 9,
      "name": "Munkidori",
      "found": 1,
      "total": 1,
      "pct": 100.0,
      "dist": [
        {
          "copies": 1,
          "players": 1,
          "percent": 100.0
        }
      ],
      "set": "TWM",
      "number": "095",
      "uid": "Munkidori::TWM::095"
    },
    {
      "rank": 10,
      "name": "N's Reshiram",
      "found": 1,
      "total": 1,
      "pct": 100.0,
      "dist": [
        {
          "copies": 1,
          "players": 1,
          "percent": 100.0
        }
      ],
      "set": "JTG",
      "number": "116",
      "uid": "N's Reshiram::JTG::116"
    },
    {
      "rank": 11,
      "name": "Fezandipiti ex",
      "found": 1,
      "total": 1,
      "pct": 100.0,
      "dist": [
        {
          "copies": 1,
          "players": 1,
          "percent": 100.0
        }
      ],
      "set": "SFA",
      "number": "038",
      "uid": "Fezandipiti ex::SFA::038"
    },
    {
      "rank": 12,
      "name": "Pecharunt",
      "found": 1,
      "total": 1,
      "pct": 100.0,
      "dist": [
        {
          "copies": 1,
          "players": 1,
          "percent": 100.0
        }
      ],
      "set": "SVP",
      "number": "149",
      "uid": "Pecharunt::SVP::149"
    },
    {
      "rank": 13,
      "name": "Arven",
      "found": 1,
      "total": 1,
      "pct": 100.0,
      "dist": [
        {
          "copies": 4,
          "players": 1,
          "percent": 100.0
        }
      ]
    },
    {
      "rank": 14,
      "name": "Iono",
      "found": 1,
      "total": 1,
      "pct": 100.0,
      "dist": [
        {
          "copies": 3,
          "players": 1,
          "percent": 100.0
        }
      ]
    },
    {
      "rank": 15,
      "name": "Brock's Scouting",
      "found": 1,
      "total": 1,
      "pct": 100.0,
      "dist": [
        {
          "copies": 3,
          "players": 1,
          "percent": 100.0
        }
      ]
    },
    {
      "rank": 16,
      "name": "Morty's Conviction",
      "found": 1,
      "total": 1,
      "pct": 100.0,
      "dist": [
        {
          "copies": 2,
          "players": 1,
          "percent": 100.0
        }
      ]
    },
    {
      "rank": 17,
      "name": "Boss's Orders",
      "found": 1,
      "total": 1,
      "pct": 100.0,
      "dist": [
        {
          "copies": 2,
          "players": 1,
          "percent": 100.0
        }
      ]
    },
    {
      "rank": 18,
      "name": "Professor Turo's Scenario",
      "found": 1,
      "total": 1,
      "pct": 100.0,
      "dist": [
        {
          "copies": 1,
          "players": 1,
          "percent": 100.0
        }
      ]
    },
    {
      "rank": 19,
      "name": "Rare Candy",
      "found": 1,
      "total": 1,
      "pct": 100.0,
      "dist": [
        {
          "copies": 3,
          "players": 1,
          "percent": 100.0
        }
      ]
    },
    {
      "rank": 20,
      "name": "Ultra Ball",
      "found": 1,
      "total": 1,
      "pct": 100.0,
      "dist": [
        {
          "copies": 3,
          "players": 1,
          "percent": 100.0
        }
      ]
    },
    {
      "rank": 21,
      "name": "Buddy-Buddy Poffin",
      "found": 1,
      "total": 1,
      "pct": 100.0,
      "dist": [
        {
          "copies": 1,
          "players": 1,
          "percent": 100.0
        }
      ]
    },
    {
      "rank": 22,
      "name": "Precious Trolley",
      "found": 1,
      "total": 1,
      "pct": 100.0,
      "dist": [
        {
          "copies": 1,
          "players": 1,
          "percent": 100.0
        }
      ]
    },
    {
      "rank": 23,
      "name": "Earthen Vessel",
      "found": 1,
      "total": 1,
      "pct": 100.0,
      "dist": [
        {
          "copies": 1,
          "players": 1,
          "percent": 100.0
        }
      ]
    },
    {
      "rank": 24,
      "name": "Counter Catcher",
      "found": 1,
      "total": 1,
      "pct": 100.0,
      "dist": [
        {
          "copies": 1,
          "players": 1,
          "percent": 100.0
        }
      ]
    },
    {
      "rank": 25,
      "name": "Switch",
      "found": 1,
      "total": 1,
      "pct": 100.0,
      "dist": [
        {
          "copies": 1,
          "players": 1,
          "percent": 100.0
        }
      ]
    },
    {
      "rank": 26,
      "name": "Super Rod",
      "found": 1,
      "total": 1,
      "pct": 100.0,
      "dist": [
        {
          "copies": 1,
          "players": 1,
          "percent": 100.0
        }
      ]
    },
    {
      "rank": 27,
      "name": "Technical Machine: Evolution",
      "found": 1,
      "total": 1,
      "pct": 100.0,
      "dist": [
        {
          "copies": 2,
          "players": 1,
          "percent": 100.0
        }
      ]
    },
    {
      "rank": 28,
      "name": "Artazon",
      "found": 1,
      "total": 1,
      "pct": 100.0,
      "dist": [
        {
          "copies": 1,
          "players": 1,
          "percent": 100.0
        }
      ]
    },
    {
      "rank": 29,
      "name": "Jamming Tower",
      "found": 1,
      "total": 1,
      "pct": 100.0,
      "dist": [
        {
          "copies": 1,
          "players": 1,
          "percent": 100.0
        }
      ]
    },
    {
      "rank": 30,
      "name": "Darkness Energy",
      "found": 1,
      "total": 1,
      "pct": 100.0,
      "dist": [
        {
          "copies": 3,
          "players": 1,
          "percent": 100.0
        }
      ]
    },
    {
      "rank": 31,
      "name": "Water Energy",
      "found": 1,
      "total": 1,
      "pct": 100.0,
      "dist": [
        {
          "copies": 3,
          "players": 1,
          "percent": 100.0
        }
      ]
    },
    {
      "rank": 32,
      "name": "Fire Energy",
      "found": 1,
      "total": 1,
      "pct": 100.0,
      "dist": [
        {
          "copies": 2,
          "players": 1,
          "percent": 100.0
        }
      ]
    },
    {
      "rank": 33,
      "name": "Psychic Energy",
      "found": 1,
      "total": 1,
      "pct": 100.0,
      "dist": [
        {
          "copies": 1,
          "players": 1,
          "percent": 100.0
        }
      ]
    }
  ]
}