{
  "deckTotal": 46,
  "items": [
    {
      "rank": 1,
      "name": "Joltik",
      "found": 46,
      "total": 46,
      "pct": 100.0,
      "dist": [
        {
          "copies": 2,
          "players": 46,
          "percent": 100.0
        }
      ],
      "set": "SCR",
      "number": "050",
      "uid": "Joltik::SCR::050",
      "category": "pokemon"
    },
    {
      "rank": 2,
      "name": "Pikachu ex",
      "found": 46,
      "total": 46,
      "pct": 100.0,
      "dist": [
        {
          "copies": 2,
          "players": 46,
          "percent": 100.0
        }
      ],
      "set": "SSP",
      "number": "057",
      "uid": "Pikachu ex::SSP::057",
      "category": "pokemon"
    },
    {
      "rank": 3,
      "name": "Iron Hands ex",
      "found": 46,
      "total": 46,
      "pct": 100.0,
      "dist": [
        {
          "copies": 2,
          "players": 46,
          "percent": 100.0
        }
      ],
      "set": "PAR",
      "number": "070",
      "uid": "Iron Hands ex::PAR::070",
      "category": "pokemon"
    },
    {
      "rank": 4,
      "name": "Miraidon ex",
      "found": 46,
      "total": 46,
      "pct": 100.0,
      "dist": [
        {
          "copies": 2,
          "players": 46,
          "percent": 100.0
        }
      ],
      "set": "SVI",
      "number": "081",
      "uid": "Miraidon ex::SVI::081",
      "category": "pokemon"
    },
    {
      "rank": 5,
      "name": "Fezandipiti ex",
      "found": 46,
      "total": 46,
      "pct": 100.0,
      "dist": [
        {
          "copies": 1,
          "players": 46,
          "percent": 100.0
        }
      ],
      "set": "SFA",
      "number": "038",
      "uid": "Fezandipiti ex::SFA::038",
      "category": "pokemon"
    },
    {
      "rank": 6,
      "name": "Mew ex",
      "found": 46,
      "total": 46,
      "pct": 100.0,
      "dist": [
        {
          "copies": 1,
          "players": 46,
          "percent": 100.0
        }
      ],
      "set": "MEW",
      "number": "151",
      "uid": "Mew ex::MEW::151",
      "category": "pokemon"
    },
    {
      "rank": 7,
      "name": "Latias ex",
      "found": 46,
      "total": 46,
      "pct": 100.0,
      "dist": [
        {
          "copies": 1,
          "players": 46,
          "percent": 100.0
        }
      ],
      "set": "SSP",
      "number": "076",
      "uid": "Latias ex::SSP::076",
      "category": "pokemon"
    },
    {
      "rank": 8,
      "name": "Bloodmoon Ursaluna ex",
      "found": 46,
      "total": 46,
      "pct": 100.0,
      "dist": [
        {
          "copies": 1,
          "players": 46,
          "percent": 100.0
        }
      ],
      "set": "TWM",
      "number": "141",
      "uid": "Bloodmoon Ursaluna ex::TWM::141",
      "category": "pokemon"
    },
    {
      "rank": 9,
      "name": "Lillie's Clefairy ex",
      "found": 46,
      "total": 46,
      "pct": 100.0,
      "dist": [
        {
          "copies": 1,
          "players": 45,
          "percent": 97.83
        },
        {
          "copies": 2,
          "players": 1,
          "percent": 2.17
        }
      ],
      "set": "JTG",
      "number": "056",
      "uid": "Lillie's Clefairy ex::JTG::056",
      "category": "pokemon"
    },
    {
      "rank": 10,
      "name": "Arven",
      "found": 46,
      "total": 46,
      "pct": 100.0,
      "dist": [
        {
          "copies": 3,
          "players": 13,
          "percent": 28.26
        },
        {
          "copies": 4,
          "players": 33,
          "percent": 71.74
        }
      ],
      "set": "OBF",
      "number": "186",
      "uid": "Arven::OBF::186",
      "category": "trainer"
    },
    {
      "rank": 11,
      "name": "Crispin",
      "found": 46,
      "total": 46,
      "pct": 100.0,
      "dist": [
        {
          "copies": 3,
          "players": 3,
          "percent": 6.52
        },
        {
          "copies": 4,
          "players": 43,
          "percent": 93.48
        }
      ],
      "set": "SCR",
      "number": "133",
      "uid": "Crispin::SCR::133",
      "category": "trainer"
    },
    {
      "rank": 12,
      "name": "Boss's Orders",
      "found": 46,
      "total": 46,
      "pct": 100.0,
      "dist": [
        {
          "copies": 3,
          "players": 2,
          "percent": 4.35
        },
        {
          "copies": 4,
          "players": 44,
          "percent": 95.65
        }
      ],
      "set": "PAL",
      "number": "172",
      "uid": "Boss's Orders::PAL::172",
      "category": "trainer"
    },
    {
      "rank": 13,
      "name": "Nest Ball",
      "found": 46,
      "total": 46,
      "pct": 100.0,
      "dist": [
        {
          "copies": 4,
          "players": 46,
          "percent": 100.0
        }
      ],
      "set": "SVI",
      "number": "181",
      "uid": "Nest Ball::SVI::181",
      "category": "trainer"
    },
    {
      "rank": 14,
      "name": "Pokégear 3.0",
      "found": 46,
      "total": 46,
      "pct": 100.0,
      "dist": [
        {
          "copies": 2,
          "players": 2,
          "percent": 4.35
        },
        {
          "copies": 3,
          "players": 32,
          "percent": 69.57
        },
        {
          "copies": 4,
          "players": 12,
          "percent": 26.09
        }
      ],
      "set": "SVI",
      "number": "186",
      "uid": "Pokégear 3.0::SVI::186",
      "category": "trainer"
    },
    {
      "rank": 15,
      "name": "Ultra Ball",
      "found": 46,
      "total": 46,
      "pct": 100.0,
      "dist": [
        {
          "copies": 2,
          "players": 1,
          "percent": 2.17
        },
        {
          "copies": 3,
          "players": 6,
          "percent": 13.04
        },
        {
          "copies": 4,
          "players": 39,
          "percent": 84.78
        }
      ],
      "set": "SVI",
      "number": "196",
      "uid": "Ultra Ball::SVI::196",
      "category": "trainer"
    },
    {
      "rank": 16,
      "name": "Prime Catcher",
      "found": 46,
      "total": 46,
      "pct": 100.0,
      "dist": [
        {
          "copies": 1,
          "players": 46,
          "percent": 100.0
        }
      ],
      "set": "TEF",
      "number": "157",
      "uid": "Prime Catcher::TEF::157",
      "category": "trainer"
    },
    {
      "rank": 17,
      "name": "Rescue Board",
      "found": 46,
      "total": 46,
      "pct": 100.0,
      "dist": [
        {
          "copies": 1,
          "players": 46,
          "percent": 100.0
        }
      ],
      "set": "TEF",
      "number": "159",
      "uid": "Rescue Board::TEF::159",
      "category": "trainer"
    },
    {
      "rank": 18,
      "name": "Grass Energy",
      "found": 46,
      "total": 46,
      "pct": 100.0,
      "dist": [
        {
          "copies": 4,
          "players": 4,
          "percent": 8.7
        },
        {
          "copies": 5,
          "players": 42,
          "percent": 91.3
        }
      ],
      "set": "SVE",
      "number": "017",
      "uid": "Grass Energy::SVE::017",
      "category": "energy"
    },
    {
      "rank": 19,
      "name": "Lightning Energy",
      "found": 46,
      "total": 46,
      "pct": 100.0,
      "dist": [
        {
          "copies": 5,
          "players": 46,
          "percent": 100.0
        }
      ],
      "set": "SVE",
      "number": "020",
      "uid": "Lightning Energy::SVE::020",
      "category": "energy"
    },
    {
      "rank": 20,
      "name": "Psychic Energy",
      "found": 46,
      "total": 46,
      "pct": 100.0,
      "dist": [
        {
          "copies": 1,
          "players": 1,
          "percent": 2.17
        },
        {
          "copies": 2,
          "players": 45,
          "percent": 97.83
        }
      ],
      "set": "SVE",
      "number": "021",
      "uid": "Psychic Energy::SVE::021",
      "category": "energy"
    },
    {
      "rank": 21,
      "name": "Metal Energy",
      "found": 46,
      "total": 46,
      "pct": 100.0,
      "dist": [
        {
          "copies": 2,
          "players": 46,
          "percent": 100.0
        }
      ],
      "set": "SVE",
      "number": "024",
      "uid": "Metal Energy::SVE::024",
      "category": "energy"
    },
    {
      "rank": 22,
      "name": "Earthen Vessel",
      "found": 45,
      "total": 46,
      "pct": 97.83,
      "dist": [
        {
          "copies": 1,
          "players": 45,
          "percent": 100.0
        }
      ],
      "set": "PAR",
      "number": "163",
      "uid": "Earthen Vessel::PAR::163",
      "category": "trainer"
    },
    {
      "rank": 23,
      "name": "Bravery Charm",
      "found": 45,
      "total": 46,
      "pct": 97.83,
      "dist": [
        {
          "copies": 1,
          "players": 22,
          "percent": 48.89
        },
        {
          "copies": 2,
          "players": 23,
          "percent": 51.11
        }
      ],
      "set": "PAL",
      "number": "173",
      "uid": "Bravery Charm::PAL::173",
      "category": "trainer"
    },
    {
      "rank": 24,
      "name": "Galvantula",
      "found": 43,
      "total": 46,
      "pct": 93.48,
      "dist": [
        {
          "copies": 1,
          "players": 43,
          "percent": 100.0
        }
      ],
      "set": "SFA",
      "number": "002",
      "uid": "Galvantula::SFA::002",
      "category": "pokemon"
    },
    {
      "rank": 25,
      "name": "Future Booster Energy Capsule",
      "found": 39,
      "total": 46,
      "pct": 84.78,
      "dist": [
        {
          "copies": 1,
          "players": 39,
          "percent": 100.0
        }
      ],
      "set": "TEF",
      "number": "149",
      "uid": "Future Booster Energy Capsule::TEF::149",
      "category": "trainer"
    },
    {
      "rank": 26,
      "name": "Iron Leaves ex",
      "found": 32,
      "total": 46,
      "pct": 69.57,
      "dist": [
        {
          "copies": 1,
          "players": 32,
          "percent": 100.0
        }
      ],
      "set": "TEF",
      "number": "025",
      "uid": "Iron Leaves ex::TEF::025",
      "category": "pokemon"
    },
    {
      "rank": 27,
      "name": "Iono",
      "found": 32,
      "total": 46,
      "pct": 69.57,
      "dist": [
        {
          "copies": 1,
          "players": 32,
          "percent": 100.0
        }
      ],
      "set": "PAL",
      "number": "185",
      "uid": "Iono::PAL::185",
      "category": "trainer"
    },
    {
      "rank": 28,
      "name": "Super Rod",
      "found": 18,
      "total": 46,
      "pct": 39.13,
      "dist": [
        {
          "copies": 1,
          "players": 18,
          "percent": 100.0
        }
      ],
      "set": "PAL",
      "number": "188",
      "uid": "Super Rod::PAL::188",
      "category": "trainer"
    },
    {
      "rank": 29,
      "name": "Exp. Share",
      "found": 16,
      "total": 46,
      "pct": 34.78,
      "dist": [
        {
          "copies": 1,
          "players": 16,
          "percent": 100.0
        }
      ],
      "set": "SVI",
      "number": "174",
      "uid": "Exp. Share::SVI::174",
      "category": "trainer"
    },
    {
      "rank": 30,
      "name": "Gravity Mountain",
      "found": 14,
      "total": 46,
      "pct": 30.43,
      "dist": [
        {
          "copies": 1,
          "players": 13,
          "percent": 92.86
        },
        {
          "copies": 2,
          "players": 1,
          "percent": 7.14
        }
      ],
      "set": "SSP",
      "number": "177",
      "uid": "Gravity Mountain::SSP::177",
      "category": "trainer"
    },
    {
      "rank": 31,
      "name": "Night Stretcher",
      "found": 12,
      "total": 46,
      "pct": 26.09,
      "dist": [
        {
          "copies": 1,
          "players": 12,
          "percent": 100.0
        }
      ],
      "set": "SFA",
      "number": "061",
      "uid": "Night Stretcher::SFA::061",
      "category": "trainer"
    },
    {
      "rank": 32,
      "name": "Powerglass",
      "found": 11,
      "total": 46,
      "pct": 23.91,
      "dist": [
        {
          "copies": 1,
          "players": 11,
          "percent": 100.0
        }
      ],
      "set": "SFA",
      "number": "063",
      "uid": "Powerglass::SFA::063",
      "category": "trainer"
    },
    {
      "rank": 33,
      "name": "Vitality Band",
      "found": 11,
      "total": 46,
      "pct": 23.91,
      "dist": [
        {
          "copies": 1,
          "players": 11,
          "percent": 100.0
        }
      ],
      "set": "SVI",
      "number": "197",
      "uid": "Vitality Band::SVI::197",
      "category": "trainer"
    },
    {
      "rank": 34,
      "name": "Maractus",
      "found": 10,
      "total": 46,
      "pct": 21.74,
      "dist": [
        {
          "copies": 1,
          "players": 10,
          "percent": 100.0
        }
      ],
      "set": "JTG",
      "number": "008",
      "uid": "Maractus::JTG::008",
      "category": "pokemon"
    },
    {
      "rank": 35,
      "name": "Galvantula ex",
      "found": 6,
      "total": 46,
      "pct": 13.04,
      "dist": [
        {
          "copies": 1,
          "players": 6,
          "percent": 100.0
        }
      ],
      "set": "SCR",
      "number": "051",
      "uid": "Galvantula ex::SCR::051",
      "category": "pokemon"
    },
    {
      "rank": 36,
      "name": "Genesect",
      "found": 4,
      "total": 46,
      "pct": 8.7,
      "dist": [
        {
          "copies": 1,
          "players": 4,
          "percent": 100.0
        }
      ],
      "set": "SFA",
      "number": "040",
      "uid": "Genesect::SFA::040",
      "category": "pokemon"
    },
    {
      "rank": 37,
      "name": "Volcanion ex",
      "found": 4,
      "total": 46,
      "pct": 8.7,
      "dist": [
        {
          "copies": 1,
          "players": 4,
          "percent": 100.0
        }
      ],
      "set": "JTG",
      "number": "031",
      "uid": "Volcanion ex::JTG::031",
      "category": "pokemon"
    },
    {
      "rank": 38,
      "name": "Switch",
      "found": 3,
      "total": 46,
      "pct": 6.52,
      "dist": [
        {
          "copies": 1,
          "players": 3,
          "percent": 100.0
        }
      ],
      "set": "SVI",
      "number": "194",
      "uid": "Switch::SVI::194",
      "category": "trainer"
    },
    {
      "rank": 39,
      "name": "Energy Switch",
      "found": 3,
      "total": 46,
      "pct": 6.52,
      "dist": [
        {
          "copies": 1,
          "players": 3,
          "percent": 100.0
        }
      ],
      "set": "SVI",
      "number": "173",
      "uid": "Energy Switch::SVI::173",
      "category": "trainer"
    },
    {
      "rank": 40,
      "name": "Professor's Research",
      "found": 2,
      "total": 46,
      "pct": 4.35,
      "dist": [
        {
          "copies": 1,
          "players": 2,
          "percent": 100.0
        }
      ],
      "set": "JTG",
      "number": "155",
      "uid": "Professor's Research::JTG::155",
      "category": "trainer"
    },
    {
      "rank": 41,
      "name": "Counter Catcher",
      "found": 2,
      "total": 46,
      "pct": 4.35,
      "dist": [
        {
          "copies": 1,
          "players": 2,
          "percent": 100.0
        }
      ],
      "set": "PAR",
      "number": "160",
      "uid": "Counter Catcher::PAR::160",
      "category": "trainer"
    },
    {
      "rank": 42,
      "name": "Jamming Tower",
      "found": 2,
      "total": 46,
      "pct": 4.35,
      "dist": [
        {
          "copies": 1,
          "players": 2,
          "percent": 100.0
        }
      ],
      "set": "TWM",
      "number": "153",
      "uid": "Jamming Tower::TWM::153",
      "category": "trainer"
    },
    {
      "rank": 43,
      "name": "Judge",
      "found": 1,
      "total": 46,
      "pct": 2.17,
      "dist": [
        {
          "copies": 1,
          "players": 1,
          "percent": 100.0
        }
      ],
      "set": "SVI",
      "number": "176",
      "uid": "Judge::SVI::176",
      "category": "trainer"
    },
    {
      "rank": 44,
      "name": "Heavy Baton",
      "found": 1,
      "total": 46,
      "pct": 2.17,
      "dist": [
        {
          "copies": 1,
          "players": 1,
          "percent": 100.0
        }
      ],
      "set": "TEF",
      "number": "151",
      "uid": "Heavy Baton::TEF::151",
      "category": "trainer"
    },
    {
      "rank": 45,
      "name": "Town Store",
      "found": 1,
      "total": 46,
      "pct": 2.17,
      "dist": [
        {
          "copies": 1,
          "players": 1,
          "percent": 100.0
        }
      ],
      "set": "OBF",
      "number": "196",
      "uid": "Town Store::OBF::196",
      "category": "trainer"
    },
    {
      "rank": 46,
      "name": "Iron Bundle",
      "found": 1,
      "total": 46,
      "pct": 2.17,
      "dist": [
        {
          "copies": 1,
          "players": 1,
          "percent": 100.0
        }
      ],
      "set": "PAR",
      "number": "056",
      "uid": "Iron Bundle::PAR::056",
      "category": "pokemon"
    },
    {
      "rank": 47,
      "name": "Cyrano",
      "found": 1,
      "total": 46,
      "pct": 2.17,
      "dist": [
        {
          "copies": 2,
          "players": 1,
          "percent": 100.0
        }
      ],
      "set": "SSP",
      "number": "170",
      "uid": "Cyrano::SSP::170",
      "category": "trainer"
    },
    {
      "rank": 48,
      "name": "Wellspring Mask Ogerpon ex",
      "found": 1,
      "total": 46,
      "pct": 2.17,
      "dist": [
        {
          "copies": 1,
          "players": 1,
          "percent": 100.0
        }
      ],
      "set": "TWM",
      "number": "064",
      "uid": "Wellspring Mask Ogerpon ex::TWM::064",
      "category": "pokemon"
    },
    {
      "rank": 49,
      "name": "Water Energy",
      "found": 1,
      "total": 46,
      "pct": 2.17,
      "dist": [
        {
          "copies": 1,
          "players": 1,
          "percent": 100.0
        }
      ],
      "set": "SVE",
      "number": "019",
      "uid": "Water Energy::SVE::019",
      "category": "energy"
    },
    {
      "rank": 50,
      "name": "Picnic Basket",
      "found": 1,
      "total": 46,
      "pct": 2.17,
      "dist": [
        {
          "copies": 1,
          "players": 1,
          "percent": 100.0
        }
      ],
      "set": "SVI",
      "number": "184",
      "uid": "Picnic Basket::SVI::184",
      "category": "trainer"
    },
    {
      "rank": 51,
      "name": "Chien-Pao",
      "found": 1,
      "total": 46,
      "pct": 2.17,
      "dist": [
        {
          "copies": 1,
          "players": 1,
          "percent": 100.0
        }
      ],
      "set": "SSP",
      "number": "056",
      "uid": "Chien-Pao::SSP::056",
      "category": "pokemon"
    }
  ]
}